automr/__init__.py
automr/addons.py
automr/anal_fch.py
automr/autocas.py
automr/cidump.py
automr/deltascf.py
automr/driver.py
automr/dump_mat.py
automr/guess.py
automr/mcpdft.py
automr/numint.py
automr/scan.py
automr/stability.py
automr/timing.py
automr/util.py
pyautomr-0.3.1.dist-info/licenses/LICENSE
pyautomr-0.3.1.dist-info/METADATA
pyautomr-0.3.1.dist-info/WHEEL
pyautomr-0.3.1.dist-info/top_level.txt
pyautomr-0.3.1.dist-info/RECORD
