Metadata-Version: 2.4
Name: pyAutoMR
Version: 0.3.1
Summary: Automatic MR based on PySCF
Author-email: Shirong Wang <srwang20@fudan.edu.cn>
Project-URL: Homepage, https://github.com/hebrewsnabla/pyAutoMR
Project-URL: Bug Tracker, https://github.com/hebrewsnabla/pyAutoMR/issues
Classifier: Programming Language :: Python :: 3
Classifier: License :: OSI Approved :: Apache Software License
Classifier: Operating System :: POSIX
Requires-Python: >=3.8
License-File: LICENSE
Dynamic: license-file
